setup.py
cn_treasury_curve/__init__.py
cn_treasury_curve/data.py
cn_treasury_curve.egg-info/PKG-INFO
cn_treasury_curve.egg-info/SOURCES.txt
cn_treasury_curve.egg-info/dependency_links.txt
cn_treasury_curve.egg-info/entry_points.txt
cn_treasury_curve.egg-info/requires.txt
cn_treasury_curve.egg-info/top_level.txt
cn_treasury_curve/xlsx/2002.xlsx
cn_treasury_curve/xlsx/2003.xlsx
cn_treasury_curve/xlsx/2004.xlsx
cn_treasury_curve/xlsx/2005.xlsx
cn_treasury_curve/xlsx/2006.xlsx
cn_treasury_curve/xlsx/2007.xlsx
cn_treasury_curve/xlsx/2008.xlsx
cn_treasury_curve/xlsx/2009.xlsx
cn_treasury_curve/xlsx/2010.xlsx
cn_treasury_curve/xlsx/2011.xlsx
cn_treasury_curve/xlsx/2012.xlsx
cn_treasury_curve/xlsx/2013.xlsx
cn_treasury_curve/xlsx/2014.xlsx
cn_treasury_curve/xlsx/2015.xlsx
cn_treasury_curve/xlsx/2016.xlsx
cn_treasury_curve/xlsx/__init__.py