Metadata-Version: 1.0
Name: cn-treasury-curve
Version: 0.5
Summary: Collection Treasury Curve data from China Bond
Home-page: https://github.com/rainx/cn_treasury_curve.git
Author: rainx
Author-email: i@rainx.cn
License: MIT
Keywords: china bond Treasury curve stock
Platform: UNKNOWN
